deploy_skipper.py
deploy_skipper-0.0.1.dist-info/METADATA
deploy_skipper-0.0.1.dist-info/WHEEL
deploy_skipper-0.0.1.dist-info/entry_points.txt
deploy_skipper-0.0.1.dist-info/RECORD
