Metadata-Version: 2.4
Name: deploy-skipper
Version: 0.0.1
Summary: A CLI utility to detect if a project requires a deployment based on a .deployignore file
License: MIT
Author: Philipp Zettl
Requires-Python: >=3.10,<3.14
Classifier: License :: OSI Approved :: MIT License
Classifier: Programming Language :: Python :: 3
Classifier: Programming Language :: Python :: 3.10
Classifier: Programming Language :: Python :: 3.11
Classifier: Programming Language :: Python :: 3.12
Classifier: Programming Language :: Python :: 3.13
